mlbenchkit/__init__.py
mlbenchkit/benchmarks.py
mlbenchkit/cli.py
mlbenchkit/specs.py
mlbenchkit/utils.py
mlbenchkit-0.1.0.dist-info/licenses/LICENSE
mlbenchkit-0.1.0.dist-info/METADATA
mlbenchkit-0.1.0.dist-info/WHEEL
mlbenchkit-0.1.0.dist-info/entry_points.txt
mlbenchkit-0.1.0.dist-info/top_level.txt
mlbenchkit-0.1.0.dist-info/RECORD
