Metadata-Version: 2.4
Name: mlbenchkit
Version: 0.1.0
Summary: Cross-platform ML benchmarking toolkit (CPU/GPU + system specs) for Windows and macOS.
Author: Muhammad Rashid
License: MIT License
Project-URL: Homepage, https://github.com/rashidrao-pk/mlbenchkit
Project-URL: Repository, https://github.com/rashidrao-pk/mlbenchkit
Project-URL: Issues, https://github.com/rashidrao-pk/mlbenchkit/issues
Keywords: benchmark,machine-learning,pytorch,cuda,mps,performance,profiling
Classifier: Development Status :: 3 - Alpha
Classifier: Intended Audience :: Developers
Classifier: Intended Audience :: Science/Research
Classifier: Topic :: Scientific/Engineering :: Artificial Intelligence
Classifier: Topic :: System :: Benchmark
Classifier: License :: OSI Approved :: MIT License
Classifier: Programming Language :: Python :: 3
Classifier: Programming Language :: Python :: 3 :: Only
Classifier: Programming Language :: Python :: 3.9
Classifier: Programming Language :: Python :: 3.10
Classifier: Programming Language :: Python :: 3.11
Classifier: Operating System :: Microsoft :: Windows
Classifier: Operating System :: MacOS
Classifier: Operating System :: POSIX :: Linux
Requires-Python: >=3.9
License-File: LICENSE
Requires-Dist: psutil>=5.9
Requires-Dist: py-cpuinfo>=9.0
Provides-Extra: torch
Requires-Dist: torch>=2.0; extra == "torch"
Provides-Extra: sklearn
Requires-Dist: scikit-learn>=1.2; extra == "sklearn"
Requires-Dist: numpy>=1.23; extra == "sklearn"
Dynamic: license-file
